aru.py
aru-0.0.1.dist-info/LICENSE
aru-0.0.1.dist-info/METADATA
aru-0.0.1.dist-info/WHEEL
aru-0.0.1.dist-info/top_level.txt
aru-0.0.1.dist-info/RECORD
