Metadata-Version: 2.1
Name: aru
Version: 0.0.1
Summary: All in one mathematical function module
Author: Shree Aru Bisoi
Classifier: Programming Language :: Python :: 3
Classifier: License :: OSI Approved :: MIT License
Classifier: Operating System :: OS Independent
Requires-Python: >=3.6
License-File: LICENSE
